{
	"template": "obsession",

	"href": "les-jours-c-quoi",

	"color": 7,
	"name":  "« Les Jours », c'est quoi ?",
	"title": "« Les Jours », c'est quoi ?",
	"subtitle": "C'est qui ? Comment ça marche ? Combien ça coûte ?",
	"desc": "<p>Face au torrent de l’info éphémère, <i>Les Jours</i>, c’est le nouveau média en ligne qui creuse ses obsessions au cœur de l’actualité et ne les lâche pas.<p>
<p><i>Les Jours</i> défendent un journalisme singulier, curieux, tenace, emmené par des têtes de pioche.</p>",

	"episodes": [
		"episode:les-jours-c-quoi/les-jours-le-projet",
		"episode:les-jours-c-quoi/les-jours-le-pilote",
		"episode:les-jours-c-quoi/les-jours-tuto-obsession",
		"episode:les-jours-c-quoi/les-jours-navigation",
		"episode:les-jours-c-quoi/les-jours-combien",
		"episode:les-jours-c-quoi/les-jours-l-equipe"
	],

	"people": [
		{
			"href":     "#",
			"img":      "img/olivier-bertrand.jpg",
			"alt":      "",
			"title":    "Olivier Bertrand",
			"subtitle": "Obsession Turquie"
		},
		{
			"href":     "#",
			"img":      "img/jc-besson.jpg",
			"alt":      "",
			"title":    "Jean-Christophe Besson",
			"subtitle": "Obsession snake"
		},
		{
			"href":     "#",
			"img":      "img/jbg.jpg",
			"alt":      "",
			"title":    "Jérôme Bourreau-Guggenheim",
			"subtitle": "Obsession"
		},
		{
			"href":     "#",
			"img":      "img/sebastien-calvet.jpg",
			"alt":      "",
			"title":    "Sébastien Calvet",
			"subtitle": "Obsession photo"
		},
		{
			"href":     "#",
			"img":      "img/nicolas-cori.jpg",
			"alt":      "",
			"title":    "Nicolas Cori",
			"subtitle": "Obsession jonglage"
		},
		{
			"href":     "#",
			"img":      "img/sophian-fanen",
			"alt":      "",
			"title":    "Sophian Fanen",
			"subtitle": "Obsession Adele"
		},
		{
			"href":     "#",
			"img":      "img/garriberts.jpg",
			"alt":      "",
			"title":    "Les Garriberts",
			"subtitle": "Obsession obsession"
		},
		{
			"href":     "#",
			"img":      "img/louis-garrel.jpg",
			"alt":      "",
			"title":    "Alice Géraud",
			"subtitle": "Obsession Louis Garrel"
		},
		{
			"href":     "#",
			"img":      "img/antoine-guiral.jpg",
			"alt":      "",
			"title":    "Antoine Guiral",
			"subtitle": "Obsession politique et chaîne de vélo"
		},
		{
			"href":     "#",
			"img":      "img/nicolas-le-gall.jpg",
			"alt":      "",
			"title":    "Nicolas Le Gall",
			"subtitle": "Obsession Japon"
		},
		{
			"href":     "#",
			"img":      "img/augustin-naepels.jpg",
			"alt":      "",
			"title":    "Augustin Naepels",
			"subtitle": "Obsession outre-mer"
		},
		{
			"href":     "#",
			"img":      "img/camille-polloni.jpg",
			"alt":      "",
			"title":    "Camille Polloni",
			"subtitle": "Obsession chercher"
		},
		{
			"href":     "#",
			"img":      "img/charlotte-rotman.jpg",
			"alt":      "",
			"title":    "Charlotte Rotman",
			"subtitle": "Obsession curiosité"
		},
		{
			"href":     "#",
			"img":      "img/david-thomson.jpg",
			"alt":      "",
			"title":    "David Thomson",
			"subtitle": "Obsession jihadiste"
		}
	],

	"images": [
		{ "href": "#", "img": "img/header-projet.jpg" },
		{ "href": "#", "img": "img/header-pilote.jpg" },
		{ "href": "#", "img": "img/header-obsession.jpg" },
		{ "href": "#", "img": "img/header-navigation.jpg" },
		{ "href": "#", "img": "img/header-combien.jpg" },
		{ "href": "#", "img": "img/header-equipe.jpg" }
	],

	"places": [
		{
			"img":   "img/header-projet.jpg",
			"title": "Les « Jours », c'est ici",
			"href":  "https://www.google.fr/maps/place/14+Rue+de+Rouen,+75019+Paris/@48.8877697,2.3719155,17z/data=!3m1!4b1!4m2!3m1!1s0x47e66dd72345392d:0xf4956a1d12fd644"
		}
	],

	"documents": [
		{
			"id": "telechargements",
			"title": "Téléchargements",
			"icon": "download",
			"items": [
				{
					"href": "doc/article-le-monde-fevrier.pdf",
					"title": "« L’aube va se lever très vite sur Les Jours »",
					"desc": "Un article du <i>Monde</> consacré aux <i>Jours</i>."
				}
			]
		}
	]
}